{"version":"1","myst":"1.8.3","references":[{"kind":"page","data":"/content/index.json","url":"/"},{"kind":"page","data":"/content/practica1-fixed2.json","url":"/practica1-fixed2"},{"identifier":"8xcqhngehq57","html_id":"id-8xcqhngehq57","kind":"block:notebook-content","data":"/content/practica1-fixed2.json","url":"/practica1-fixed2"},{"identifier":"representaci-n-de-n-meros-reales-en-python","kind":"heading","data":"/content/practica1-fixed2.json","url":"/practica1-fixed2","implicit":true},{"identifier":"h07he7_zers9","html_id":"h07he7-zers9","kind":"block:notebook-code","data":"/content/practica1-fixed2.json","url":"/practica1-fixed2"},{"identifier":"h07he7_zers9-code","html_id":"h07he7-zers9-code","kind":"code","data":"/content/practica1-fixed2.json","url":"/practica1-fixed2"},{"identifier":"h07he7_zers9-outputs","html_id":"h07he7-zers9-outputs","kind":"outputs","data":"/content/practica1-fixed2.json","url":"/practica1-fixed2"},{"identifier":"h07he7_zers9-outputs-0","html_id":"h07he7-zers9-outputs-0","kind":"output","data":"/content/practica1-fixed2.json","url":"/practica1-fixed2"},{"identifier":"fpd25imbl7ve","kind":"block:notebook-content","data":"/content/practica1-fixed2.json","url":"/practica1-fixed2"},{"identifier":"convertir-un-n-mero-real-en-un-n-mero-flotante","kind":"heading","data":"/content/practica1-fixed2.json","url":"/practica1-fixed2","implicit":true},{"identifier":"xvbahucawixk","kind":"block:notebook-content","data":"/content/practica1-fixed2.json","url":"/practica1-fixed2"},{"identifier":"n1-05dzgmvwv","kind":"block:notebook-code","data":"/content/practica1-fixed2.json","url":"/practica1-fixed2"},{"identifier":"n1-05dzgmvwv-code","kind":"code","data":"/content/practica1-fixed2.json","url":"/practica1-fixed2"},{"identifier":"n1-05dzgmvwv-outputs","kind":"outputs","data":"/content/practica1-fixed2.json","url":"/practica1-fixed2"},{"identifier":"n1-05dzgmvwv-outputs-0","kind":"output","data":"/content/practica1-fixed2.json","url":"/practica1-fixed2"},{"identifier":"lsvo3w6t2zs_","html_id":"lsvo3w6t2zs","kind":"block:notebook-content","data":"/content/practica1-fixed2.json","url":"/practica1-fixed2"},{"identifier":"operaciones-con-flotantes","kind":"heading","data":"/content/practica1-fixed2.json","url":"/practica1-fixed2","implicit":true},{"identifier":"9onwhorq3qif","html_id":"id-9onwhorq3qif","kind":"block:notebook-content","data":"/content/practica1-fixed2.json","url":"/practica1-fixed2"},{"identifier":"j7orbx7c2yqq","kind":"block:notebook-code","data":"/content/practica1-fixed2.json","url":"/practica1-fixed2"},{"identifier":"j7orbx7c2yqq-code","kind":"code","data":"/content/practica1-fixed2.json","url":"/practica1-fixed2"},{"identifier":"j7orbx7c2yqq-outputs","kind":"outputs","data":"/content/practica1-fixed2.json","url":"/practica1-fixed2"},{"identifier":"j7orbx7c2yqq-outputs-0","kind":"output","data":"/content/practica1-fixed2.json","url":"/practica1-fixed2"},{"identifier":"5zf9e2rgiczp","html_id":"id-5zf9e2rgiczp","kind":"block:notebook-content","data":"/content/practica1-fixed2.json","url":"/practica1-fixed2"},{"identifier":"pr-ctica-1-1-uso-de-n-meros-de-punto-flotante-en-python","kind":"heading","data":"/content/practica1-fixed2.json","url":"/practica1-fixed2","implicit":true},{"identifier":"rdrbolxmqnyj","kind":"block:notebook-code","data":"/content/practica1-fixed2.json","url":"/practica1-fixed2"},{"identifier":"rdrbolxmqnyj-code","kind":"code","data":"/content/practica1-fixed2.json","url":"/practica1-fixed2"},{"identifier":"rdrbolxmqnyj-outputs","kind":"outputs","data":"/content/practica1-fixed2.json","url":"/practica1-fixed2"},{"identifier":"rdrbolxmqnyj-outputs-0","kind":"output","data":"/content/practica1-fixed2.json","url":"/practica1-fixed2"},{"identifier":"sl8r-lyzri2z","kind":"block:notebook-code","data":"/content/practica1-fixed2.json","url":"/practica1-fixed2"},{"identifier":"sl8r-lyzri2z-code","kind":"code","data":"/content/practica1-fixed2.json","url":"/practica1-fixed2"},{"identifier":"sl8r-lyzri2z-outputs","kind":"outputs","data":"/content/practica1-fixed2.json","url":"/practica1-fixed2"},{"identifier":"sl8r-lyzri2z-outputs-0","kind":"output","data":"/content/practica1-fixed2.json","url":"/practica1-fixed2"},{"identifier":"sdhyiw7cspk5","kind":"block:notebook-code","data":"/content/practica1-fixed2.json","url":"/practica1-fixed2"},{"identifier":"sdhyiw7cspk5-code","kind":"code","data":"/content/practica1-fixed2.json","url":"/practica1-fixed2"},{"identifier":"sdhyiw7cspk5-outputs","kind":"outputs","data":"/content/practica1-fixed2.json","url":"/practica1-fixed2"},{"identifier":"sdhyiw7cspk5-outputs-0","kind":"output","data":"/content/practica1-fixed2.json","url":"/practica1-fixed2"},{"identifier":"suzn8gkz6gtt","kind":"block:notebook-content","data":"/content/practica1-fixed2.json","url":"/practica1-fixed2"},{"identifier":"propiedades-de-campo-de-los-n-meros-reales","kind":"heading","data":"/content/practica1-fixed2.json","url":"/practica1-fixed2","implicit":true},{"identifier":"wgszdr_d2bsc","html_id":"wgszdr-d2bsc","kind":"block:notebook-content","data":"/content/practica1-fixed2.json","url":"/practica1-fixed2"},{"identifier":"pr-ctica-1-2-los-n-meros-flotantes-son-un-campo","kind":"heading","data":"/content/practica1-fixed2.json","url":"/practica1-fixed2","implicit":true},{"identifier":"d3f3z7dm6sd5","kind":"block:notebook-code","data":"/content/practica1-fixed2.json","url":"/practica1-fixed2"},{"identifier":"d3f3z7dm6sd5-code","kind":"code","data":"/content/practica1-fixed2.json","url":"/practica1-fixed2"},{"identifier":"d3f3z7dm6sd5-outputs","kind":"outputs","data":"/content/practica1-fixed2.json","url":"/practica1-fixed2"},{"identifier":"xtnsraqa3azg","kind":"block:notebook-code","data":"/content/practica1-fixed2.json","url":"/practica1-fixed2"},{"identifier":"xtnsraqa3azg-code","kind":"code","data":"/content/practica1-fixed2.json","url":"/practica1-fixed2"},{"identifier":"xtnsraqa3azg-outputs","kind":"outputs","data":"/content/practica1-fixed2.json","url":"/practica1-fixed2"},{"identifier":"6xhrl1bm8myq","html_id":"id-6xhrl1bm8myq","kind":"block:notebook-code","data":"/content/practica1-fixed2.json","url":"/practica1-fixed2"},{"identifier":"6xhrl1bm8myq-code","html_id":"id-6xhrl1bm8myq-code","kind":"code","data":"/content/practica1-fixed2.json","url":"/practica1-fixed2"},{"identifier":"6xhrl1bm8myq-outputs","html_id":"id-6xhrl1bm8myq-outputs","kind":"outputs","data":"/content/practica1-fixed2.json","url":"/practica1-fixed2"},{"identifier":"6xhrl1bm8myq-outputs-0","html_id":"id-6xhrl1bm8myq-outputs-0","kind":"output","data":"/content/practica1-fixed2.json","url":"/practica1-fixed2"},{"identifier":"jy83mopv2vsv","kind":"block:notebook-code","data":"/content/practica1-fixed2.json","url":"/practica1-fixed2"},{"identifier":"jy83mopv2vsv-code","kind":"code","data":"/content/practica1-fixed2.json","url":"/practica1-fixed2"},{"identifier":"jy83mopv2vsv-outputs","kind":"outputs","data":"/content/practica1-fixed2.json","url":"/practica1-fixed2"},{"identifier":"jy83mopv2vsv-outputs-0","kind":"output","data":"/content/practica1-fixed2.json","url":"/practica1-fixed2"},{"identifier":"89yy2gxg9ead","html_id":"id-89yy2gxg9ead","kind":"block:notebook-code","data":"/content/practica1-fixed2.json","url":"/practica1-fixed2"},{"identifier":"89yy2gxg9ead-code","html_id":"id-89yy2gxg9ead-code","kind":"code","data":"/content/practica1-fixed2.json","url":"/practica1-fixed2"},{"identifier":"89yy2gxg9ead-outputs","html_id":"id-89yy2gxg9ead-outputs","kind":"outputs","data":"/content/practica1-fixed2.json","url":"/practica1-fixed2"},{"identifier":"89yy2gxg9ead-outputs-0","html_id":"id-89yy2gxg9ead-outputs-0","kind":"output","data":"/content/practica1-fixed2.json","url":"/practica1-fixed2"},{"identifier":"ptu0ij4bevar","kind":"block:notebook-code","data":"/content/practica1-fixed2.json","url":"/practica1-fixed2"},{"identifier":"ptu0ij4bevar-code","kind":"code","data":"/content/practica1-fixed2.json","url":"/practica1-fixed2"},{"identifier":"ptu0ij4bevar-outputs","kind":"outputs","data":"/content/practica1-fixed2.json","url":"/practica1-fixed2"},{"identifier":"ptu0ij4bevar-outputs-0","kind":"output","data":"/content/practica1-fixed2.json","url":"/practica1-fixed2"},{"identifier":"slx3pclnyr0-","html_id":"slx3pclnyr0","kind":"block:notebook-code","data":"/content/practica1-fixed2.json","url":"/practica1-fixed2"},{"identifier":"slx3pclnyr0--code","html_id":"slx3pclnyr0-code","kind":"code","data":"/content/practica1-fixed2.json","url":"/practica1-fixed2"},{"identifier":"slx3pclnyr0--outputs","html_id":"slx3pclnyr0-outputs","kind":"outputs","data":"/content/practica1-fixed2.json","url":"/practica1-fixed2"},{"identifier":"slx3pclnyr0--outputs-0","html_id":"slx3pclnyr0-outputs-0","kind":"output","data":"/content/practica1-fixed2.json","url":"/practica1-fixed2"},{"identifier":"t5l8jg4szd8j","kind":"block:notebook-content","data":"/content/practica1-fixed2.json","url":"/practica1-fixed2"},{"identifier":"propiedades-de-orden-de-los-n-mero-reales","kind":"heading","data":"/content/practica1-fixed2.json","url":"/practica1-fixed2","implicit":true},{"identifier":"rqcea8kvpkdz","kind":"block:notebook-code","data":"/content/practica1-fixed2.json","url":"/practica1-fixed2"},{"identifier":"rqcea8kvpkdz-code","kind":"code","data":"/content/practica1-fixed2.json","url":"/practica1-fixed2"},{"identifier":"rqcea8kvpkdz-outputs","kind":"outputs","data":"/content/practica1-fixed2.json","url":"/practica1-fixed2"},{"identifier":"rqcea8kvpkdz-outputs-0","kind":"output","data":"/content/practica1-fixed2.json","url":"/practica1-fixed2"},{"identifier":"rqcea8kvpkdz-outputs-1","kind":"output","data":"/content/practica1-fixed2.json","url":"/practica1-fixed2"},{"identifier":"gg8em6ezqfag","kind":"block:notebook-content","data":"/content/practica1-fixed2.json","url":"/practica1-fixed2"},{"identifier":"ue4r95iwszat","kind":"block:notebook-code","data":"/content/practica1-fixed2.json","url":"/practica1-fixed2"},{"identifier":"ue4r95iwszat-code","kind":"code","data":"/content/practica1-fixed2.json","url":"/practica1-fixed2"},{"identifier":"ue4r95iwszat-outputs","kind":"outputs","data":"/content/practica1-fixed2.json","url":"/practica1-fixed2"},{"identifier":"ue4r95iwszat-outputs-0","kind":"output","data":"/content/practica1-fixed2.json","url":"/practica1-fixed2"},{"identifier":"anqeeu0rx65r","kind":"block:notebook-content","data":"/content/practica1-fixed2.json","url":"/practica1-fixed2"},{"identifier":"valor-absoluto","kind":"heading","data":"/content/practica1-fixed2.json","url":"/practica1-fixed2","implicit":true},{"identifier":"_ke3wbdkezvs","html_id":"id-ke3wbdkezvs","kind":"block:notebook-code","data":"/content/practica1-fixed2.json","url":"/practica1-fixed2"},{"identifier":"_ke3wbdkezvs-code","html_id":"id-ke3wbdkezvs-code","kind":"code","data":"/content/practica1-fixed2.json","url":"/practica1-fixed2"},{"identifier":"_ke3wbdkezvs-outputs","html_id":"id-ke3wbdkezvs-outputs","kind":"outputs","data":"/content/practica1-fixed2.json","url":"/practica1-fixed2"},{"identifier":"_ke3wbdkezvs-outputs-0","html_id":"id-ke3wbdkezvs-outputs-0","kind":"output","data":"/content/practica1-fixed2.json","url":"/practica1-fixed2"},{"identifier":"xc2-mwq7u0cu","kind":"block:notebook-content","data":"/content/practica1-fixed2.json","url":"/practica1-fixed2"},{"identifier":"valor-absoluto-de-la-diferencia-de-dos-n-meros-reales","kind":"heading","data":"/content/practica1-fixed2.json","url":"/practica1-fixed2","implicit":true},{"identifier":"ujqkehk22utk","kind":"block:notebook-code","data":"/content/practica1-fixed2.json","url":"/practica1-fixed2"},{"identifier":"ujqkehk22utk-code","kind":"code","data":"/content/practica1-fixed2.json","url":"/practica1-fixed2"},{"identifier":"ujqkehk22utk-outputs","kind":"outputs","data":"/content/practica1-fixed2.json","url":"/practica1-fixed2"},{"identifier":"ujqkehk22utk-outputs-0","kind":"output","data":"/content/practica1-fixed2.json","url":"/practica1-fixed2"},{"identifier":"ujqkehk22utk-outputs-1","kind":"output","data":"/content/practica1-fixed2.json","url":"/practica1-fixed2"},{"identifier":"sj1miye3cz_2","html_id":"sj1miye3cz-2","kind":"block:notebook-content","data":"/content/practica1-fixed2.json","url":"/practica1-fixed2"},{"identifier":"pr-ctica-1-3-distancia-entre-dos-n-meros-reales","kind":"heading","data":"/content/practica1-fixed2.json","url":"/practica1-fixed2","implicit":true},{"identifier":"cozkv16faodj","kind":"block:notebook-content","data":"/content/practica1-fixed2.json","url":"/practica1-fixed2"},{"identifier":"funciones-en-python","kind":"heading","data":"/content/practica1-fixed2.json","url":"/practica1-fixed2","implicit":true},{"identifier":"rc3um9tzu4ig","kind":"block:notebook-content","data":"/content/practica1-fixed2.json","url":"/practica1-fixed2"},{"identifier":"rc3um9tzu4ig-code","kind":"code","data":"/content/practica1-fixed2.json","url":"/practica1-fixed2"},{"identifier":"mzuye4xjywec","kind":"block:notebook-content","data":"/content/practica1-fixed2.json","url":"/practica1-fixed2"},{"identifier":"0fkf2n0h1ns4","html_id":"id-0fkf2n0h1ns4","kind":"block:notebook-content","data":"/content/practica1-fixed2.json","url":"/practica1-fixed2"},{"identifier":"0fkf2n0h1ns4-code","html_id":"id-0fkf2n0h1ns4-code","kind":"code","data":"/content/practica1-fixed2.json","url":"/practica1-fixed2"},{"identifier":"eqloxfevzoui","kind":"block:notebook-code","data":"/content/practica1-fixed2.json","url":"/practica1-fixed2"},{"identifier":"eqloxfevzoui-code","kind":"code","data":"/content/practica1-fixed2.json","url":"/practica1-fixed2"},{"identifier":"eqloxfevzoui-outputs","kind":"outputs","data":"/content/practica1-fixed2.json","url":"/practica1-fixed2"},{"identifier":"eqloxfevzoui-outputs-0","kind":"output","data":"/content/practica1-fixed2.json","url":"/practica1-fixed2"},{"identifier":"fyz1svau0-by","kind":"block:notebook-content","data":"/content/practica1-fixed2.json","url":"/practica1-fixed2"},{"identifier":"id-2-iterar-sobre-una-lista-de-n-meros","kind":"heading","data":"/content/practica1-fixed2.json","url":"/practica1-fixed2","implicit":true},{"identifier":"fyz1svau0-by-code","kind":"code","data":"/content/practica1-fixed2.json","url":"/practica1-fixed2"},{"identifier":"cla7ds8i0gai","kind":"block:notebook-code","data":"/content/practica1-fixed2.json","url":"/practica1-fixed2"},{"identifier":"cla7ds8i0gai-code","kind":"code","data":"/content/practica1-fixed2.json","url":"/practica1-fixed2"},{"identifier":"cla7ds8i0gai-outputs","kind":"outputs","data":"/content/practica1-fixed2.json","url":"/practica1-fixed2"},{"identifier":"cla7ds8i0gai-outputs-0","kind":"output","data":"/content/practica1-fixed2.json","url":"/practica1-fixed2"},{"identifier":"qzcrnx991uud","kind":"block:notebook-content","data":"/content/practica1-fixed2.json","url":"/practica1-fixed2"},{"identifier":"id-3-ejecutar-c-digo-repetidamente","kind":"heading","data":"/content/practica1-fixed2.json","url":"/practica1-fixed2","implicit":true},{"identifier":"qzcrnx991uud-code","kind":"code","data":"/content/practica1-fixed2.json","url":"/practica1-fixed2"},{"identifier":"nqryjyg31gy8","kind":"block:notebook-code","data":"/content/practica1-fixed2.json","url":"/practica1-fixed2"},{"identifier":"nqryjyg31gy8-code","kind":"code","data":"/content/practica1-fixed2.json","url":"/practica1-fixed2"},{"identifier":"nqryjyg31gy8-outputs","kind":"outputs","data":"/content/practica1-fixed2.json","url":"/practica1-fixed2"},{"identifier":"nqryjyg31gy8-outputs-0","kind":"output","data":"/content/practica1-fixed2.json","url":"/practica1-fixed2"},{"identifier":"svxtvfjpwpzd","kind":"block:notebook-code","data":"/content/practica1-fixed2.json","url":"/practica1-fixed2"},{"identifier":"svxtvfjpwpzd-code","kind":"code","data":"/content/practica1-fixed2.json","url":"/practica1-fixed2"},{"identifier":"svxtvfjpwpzd-outputs","kind":"outputs","data":"/content/practica1-fixed2.json","url":"/practica1-fixed2"},{"identifier":"svxtvfjpwpzd-outputs-0","kind":"output","data":"/content/practica1-fixed2.json","url":"/practica1-fixed2"},{"identifier":"2s3jyr3lw9p0","html_id":"id-2s3jyr3lw9p0","kind":"block:notebook-code","data":"/content/practica1-fixed2.json","url":"/practica1-fixed2"},{"identifier":"2s3jyr3lw9p0-code","html_id":"id-2s3jyr3lw9p0-code","kind":"code","data":"/content/practica1-fixed2.json","url":"/practica1-fixed2"},{"identifier":"2s3jyr3lw9p0-outputs","html_id":"id-2s3jyr3lw9p0-outputs","kind":"outputs","data":"/content/practica1-fixed2.json","url":"/practica1-fixed2"},{"identifier":"2s3jyr3lw9p0-outputs-0","html_id":"id-2s3jyr3lw9p0-outputs-0","kind":"output","data":"/content/practica1-fixed2.json","url":"/practica1-fixed2"},{"identifier":"zhbkmv5jxghf","kind":"block:notebook-content","data":"/content/practica1-fixed2.json","url":"/practica1-fixed2"},{"identifier":"id-4-iterar-sobre-una-cadena-de-texto","kind":"heading","data":"/content/practica1-fixed2.json","url":"/practica1-fixed2","implicit":true},{"identifier":"zhbkmv5jxghf-code","kind":"code","data":"/content/practica1-fixed2.json","url":"/practica1-fixed2"},{"identifier":"bfovjkv9xvoi","kind":"block:notebook-code","data":"/content/practica1-fixed2.json","url":"/practica1-fixed2"},{"identifier":"bfovjkv9xvoi-code","kind":"code","data":"/content/practica1-fixed2.json","url":"/practica1-fixed2"},{"identifier":"bfovjkv9xvoi-outputs","kind":"outputs","data":"/content/practica1-fixed2.json","url":"/practica1-fixed2"},{"identifier":"bfovjkv9xvoi-outputs-0","kind":"output","data":"/content/practica1-fixed2.json","url":"/practica1-fixed2"},{"identifier":"7bvo_2rxyvkq","html_id":"id-7bvo-2rxyvkq","kind":"block:notebook-content","data":"/content/practica1-fixed2.json","url":"/practica1-fixed2"},{"identifier":"id-5-sumar-n-meros-de-una-lista","kind":"heading","data":"/content/practica1-fixed2.json","url":"/practica1-fixed2","implicit":true},{"identifier":"7bvo_2rxyvkq-code","html_id":"id-7bvo-2rxyvkq-code","kind":"code","data":"/content/practica1-fixed2.json","url":"/practica1-fixed2"},{"identifier":"0gqhrgqkymhr","html_id":"id-0gqhrgqkymhr","kind":"block:notebook-code","data":"/content/practica1-fixed2.json","url":"/practica1-fixed2"},{"identifier":"0gqhrgqkymhr-code","html_id":"id-0gqhrgqkymhr-code","kind":"code","data":"/content/practica1-fixed2.json","url":"/practica1-fixed2"},{"identifier":"0gqhrgqkymhr-outputs","html_id":"id-0gqhrgqkymhr-outputs","kind":"outputs","data":"/content/practica1-fixed2.json","url":"/practica1-fixed2"},{"identifier":"0gqhrgqkymhr-outputs-0","html_id":"id-0gqhrgqkymhr-outputs-0","kind":"output","data":"/content/practica1-fixed2.json","url":"/practica1-fixed2"},{"identifier":"ud2saso7qqx8","kind":"block:notebook-content","data":"/content/practica1-fixed2.json","url":"/practica1-fixed2"},{"identifier":"sucesiones","kind":"heading","data":"/content/practica1-fixed2.json","url":"/practica1-fixed2","implicit":true},{"identifier":"ekyho0jiwxim","kind":"block:notebook-content","data":"/content/practica1-fixed2.json","url":"/practica1-fixed2"},{"identifier":"p_zewglczmbi","html_id":"p-zewglczmbi","kind":"block:notebook-code","data":"/content/practica1-fixed2.json","url":"/practica1-fixed2"},{"identifier":"p_zewglczmbi-code","html_id":"p-zewglczmbi-code","kind":"code","data":"/content/practica1-fixed2.json","url":"/practica1-fixed2"},{"identifier":"p_zewglczmbi-outputs","html_id":"p-zewglczmbi-outputs","kind":"outputs","data":"/content/practica1-fixed2.json","url":"/practica1-fixed2"},{"identifier":"p_zewglczmbi-outputs-0","html_id":"p-zewglczmbi-outputs-0","kind":"output","data":"/content/practica1-fixed2.json","url":"/practica1-fixed2"},{"identifier":"cn8gtjrtxqsv","kind":"block:notebook-content","data":"/content/practica1-fixed2.json","url":"/practica1-fixed2"},{"identifier":"ejercicios","kind":"heading","data":"/content/practica1-fixed2.json","url":"/practica1-fixed2","implicit":true},{"identifier":"jkdlt-pc3yd_","html_id":"jkdlt-pc3yd","kind":"block:notebook-code","data":"/content/practica1-fixed2.json","url":"/practica1-fixed2"},{"identifier":"jkdlt-pc3yd_-code","html_id":"jkdlt-pc3yd-code","kind":"code","data":"/content/practica1-fixed2.json","url":"/practica1-fixed2"},{"identifier":"jkdlt-pc3yd_-outputs","html_id":"jkdlt-pc3yd-outputs","kind":"outputs","data":"/content/practica1-fixed2.json","url":"/practica1-fixed2"},{"identifier":"r6jwjlftqrc6","kind":"block:notebook-content","data":"/content/practica1-fixed2.json","url":"/practica1-fixed2"},{"identifier":"gr-ficas-de-sucesiones","kind":"heading","data":"/content/practica1-fixed2.json","url":"/practica1-fixed2","implicit":true},{"identifier":"yeneelzf5qym","kind":"block:notebook-code","data":"/content/practica1-fixed2.json","url":"/practica1-fixed2"},{"identifier":"yeneelzf5qym-code","kind":"code","data":"/content/practica1-fixed2.json","url":"/practica1-fixed2"},{"identifier":"yeneelzf5qym-outputs","kind":"outputs","data":"/content/practica1-fixed2.json","url":"/practica1-fixed2"},{"identifier":"yeneelzf5qym-outputs-0","kind":"output","data":"/content/practica1-fixed2.json","url":"/practica1-fixed2"},{"identifier":"yeneelzf5qym-outputs-1","kind":"output","data":"/content/practica1-fixed2.json","url":"/practica1-fixed2"},{"identifier":"hy7iildl6oe0","kind":"block:notebook-content","data":"/content/practica1-fixed2.json","url":"/practica1-fixed2"},{"identifier":"scyitfgo7m6k","kind":"block:notebook-content","data":"/content/practica1-fixed2.json","url":"/practica1-fixed2"},{"identifier":"l-mite-de-una-sucesi-n","kind":"heading","data":"/content/practica1-fixed2.json","url":"/practica1-fixed2","implicit":true},{"identifier":"s8dnsznrb9c2","kind":"block:notebook-content","data":"/content/practica1-fixed2.json","url":"/practica1-fixed2"},{"identifier":"oacmonam5lj1","kind":"block:notebook-code","data":"/content/practica1-fixed2.json","url":"/practica1-fixed2"},{"identifier":"oacmonam5lj1-code","kind":"code","data":"/content/practica1-fixed2.json","url":"/practica1-fixed2"},{"identifier":"oacmonam5lj1-outputs","kind":"outputs","data":"/content/practica1-fixed2.json","url":"/practica1-fixed2"},{"identifier":"ica3gmo-vh2h","kind":"block:notebook-code","data":"/content/practica1-fixed2.json","url":"/practica1-fixed2"},{"identifier":"ica3gmo-vh2h-code","kind":"code","data":"/content/practica1-fixed2.json","url":"/practica1-fixed2"},{"identifier":"ica3gmo-vh2h-outputs","kind":"outputs","data":"/content/practica1-fixed2.json","url":"/practica1-fixed2"},{"identifier":"fqvtrycnv_rq","html_id":"fqvtrycnv-rq","kind":"block:notebook-code","data":"/content/practica1-fixed2.json","url":"/practica1-fixed2"},{"identifier":"fqvtrycnv_rq-code","html_id":"fqvtrycnv-rq-code","kind":"code","data":"/content/practica1-fixed2.json","url":"/practica1-fixed2"},{"identifier":"fqvtrycnv_rq-outputs","html_id":"fqvtrycnv-rq-outputs","kind":"outputs","data":"/content/practica1-fixed2.json","url":"/practica1-fixed2"},{"identifier":"kyrn9hqaw92q","kind":"block:notebook-code","data":"/content/practica1-fixed2.json","url":"/practica1-fixed2"},{"identifier":"kyrn9hqaw92q-code","kind":"code","data":"/content/practica1-fixed2.json","url":"/practica1-fixed2"},{"identifier":"kyrn9hqaw92q-outputs","kind":"outputs","data":"/content/practica1-fixed2.json","url":"/practica1-fixed2"},{"identifier":"iusv23zjysos","kind":"block:notebook-code","data":"/content/practica1-fixed2.json","url":"/practica1-fixed2"},{"identifier":"iusv23zjysos-code","kind":"code","data":"/content/practica1-fixed2.json","url":"/practica1-fixed2"},{"identifier":"iusv23zjysos-outputs","kind":"outputs","data":"/content/practica1-fixed2.json","url":"/practica1-fixed2"},{"identifier":"wkt-w3hqzmez","kind":"block:notebook-content","data":"/content/practica1-fixed2.json","url":"/practica1-fixed2"},{"identifier":"pr-ctica-3-2","kind":"heading","data":"/content/practica1-fixed2.json","url":"/practica1-fixed2","implicit":true},{"identifier":"likvq8lrzki5","kind":"block:notebook-code","data":"/content/practica1-fixed2.json","url":"/practica1-fixed2"},{"identifier":"likvq8lrzki5-code","kind":"code","data":"/content/practica1-fixed2.json","url":"/practica1-fixed2"},{"identifier":"likvq8lrzki5-outputs","kind":"outputs","data":"/content/practica1-fixed2.json","url":"/practica1-fixed2"}]}